CHANGELOG
LICENSE
MANIFEST.in
README.md
requirements.txt
setup.py
stb.egg-info/PKG-INFO
stb.egg-info/SOURCES.txt
stb.egg-info/dependency_links.txt
stb.egg-info/entry_points.txt
stb.egg-info/requires.txt
stb.egg-info/top_level.txt
stb_lib/__init__.py
stb_lib/api.py
stb_lib/data.py
stb_lib/questions.yaml
stb_lib/stb.py
stb_lib/libs/__init__.py
stb_lib/libs/build.py
stb_lib/libs/wizard.py
stb_lib/resources/__init__.py
stb_lib/resources/cookiecutter-security-tool-template/__init__.py
stb_lib/resources/cookiecutter-security-tool-template/cookiecutter.json
stb_lib/resources/cookiecutter-security-tool-template/{{ cookiecutter.tool_name }}/.gitignore
stb_lib/resources/cookiecutter-security-tool-template/{{ cookiecutter.tool_name }}/CHANGELOG
stb_lib/resources/cookiecutter-security-tool-template/{{ cookiecutter.tool_name }}/LICENSE
stb_lib/resources/cookiecutter-security-tool-template/{{ cookiecutter.tool_name }}/MANIFEST.in
stb_lib/resources/cookiecutter-security-tool-template/{{ cookiecutter.tool_name }}/README.md
stb_lib/resources/cookiecutter-security-tool-template/{{ cookiecutter.tool_name }}/__init__.py
stb_lib/resources/cookiecutter-security-tool-template/{{ cookiecutter.tool_name }}/requirements.txt
stb_lib/resources/cookiecutter-security-tool-template/{{ cookiecutter.tool_name }}/setup.py
stb_lib/resources/cookiecutter-security-tool-template/{{ cookiecutter.tool_name }}/{{ cookiecutter.tool_name }}_lib/__init__.py
stb_lib/resources/cookiecutter-security-tool-template/{{ cookiecutter.tool_name }}/{{ cookiecutter.tool_name }}_lib/api.py
stb_lib/resources/cookiecutter-security-tool-template/{{ cookiecutter.tool_name }}/{{ cookiecutter.tool_name }}_lib/data.py
stb_lib/resources/cookiecutter-security-tool-template/{{ cookiecutter.tool_name }}/{{ cookiecutter.tool_name }}_lib/{{ cookiecutter.tool_name }}.py
stb_lib/resources/cookiecutter-security-tool-template/{{ cookiecutter.tool_name }}/{{ cookiecutter.tool_name }}_lib/doc/__init__.py
stb_lib/resources/cookiecutter-security-tool-template/{{ cookiecutter.tool_name }}/{{ cookiecutter.tool_name }}_lib/doc/en/Makefile
