Metadata-Version: 1.1
Name: stb
Version: 1.0.3
Summary: Security Tool Builder (STB): Tool for creating hacking tools
Home-page: https://github.com/abirtone/stb
Author: Abirtone
Author-email: opensource@abirtone.com
License: BSD
Platform: UNKNOWN
Classifier: Environment :: Console
Classifier: Intended Audience :: System Administrators
Classifier: Intended Audience :: Other Audience
Classifier: License :: OSI Approved :: BSD License
Classifier: Operating System :: MacOS
Classifier: Operating System :: Microsoft :: Windows
Classifier: Operating System :: POSIX
Classifier: Programming Language :: Python :: 2
Classifier: Programming Language :: Python :: 3
Classifier: Topic :: Security
